src/FunctionalCorrectness/PRESENT/present_domand.v
module sbox(
    clk,
    x0_0,
    x1_0,
    x2_0,
    x3_0,
    x0_1,
    x1_1,
    x2_1,
    x3_1,
    r,
    Y0_0,
    Y1_0,
    Y2_0,
    Y3_0,
    Y0_1,
    Y1_1,
    Y2_1,
    Y3_1,
);
//INPUTS
    input clk;
    input  x0_0;
    input  x1_0;
    input  x2_0;
    input  x3_0;
    input  x0_1;
    input  x1_1;
    input  x2_1;
    input  x3_1;
    input  r;
//OUTPUTS
    output reg  Y0_0;
    output reg  Y1_0;
    output reg  Y2_0;
    output reg  Y3_0;
    output reg  Y0_1;
    output reg  Y1_1;
    output reg  Y2_1;
    output reg  Y3_1;
//Intermediate values
    wire x0_0_inp;
    wire x1_0_inp;
    wire x2_0_inp;
    wire x3_0_inp;
    reg z3_assgn3;
    wire x0_1_inp;
    wire x1_1_inp;
    wire x2_1_inp;
    wire x3_1_inp;
    reg z5_assgn5;
    wire r_inp;
    wire L0_0;
    wire L1_0;
    wire z239_assgn239;
    reg z239_assgn2390;
    reg z45_assgn45;
    wire z241_assgn241;
    reg z241_assgn2410;
    reg z46_assgn46;
    wire L8_0;
    reg x0_0_inp_reg;
    wire L5_0;
    wire L0_1;
    wire L1_1;
    wire z251_assgn251;
    reg z251_assgn2510;
    reg z53_assgn53;
    wire z253_assgn253;
    reg z253_assgn2530;
    reg z54_assgn54;
    wire L8_1;
    reg x0_1_inp_reg;
    wire L5_1;
    wire Q0_0;
    wire Q1_0;
    wire Q3_0;
    wire Q4_0;
    wire Q0_1;
    wire Q1_1;
    wire Q3_1;
    wire Q4_1;
    reg Q1_0_reg;
    reg x2_0_inp_reg;
    wire L2_0;
    reg Q0_0_reg;
    wire L3_0;
    reg Q1_1_reg;
    reg x2_1_inp_reg;
    wire L2_1;
    reg Q0_1_reg;
    wire L3_1;
    wire p2_domand0;
    wire i1_domand0;
    wire p3_domand0;
    wire i2_domand0;
    wire p1_domand0;
    wire p4_domand0;
    reg i1_domand0_reg;
    wire T0_0;
    reg i2_domand0_reg;
    wire T0_1;
    wire z1_assgn1;
    reg L10_0;
    wire z2_assgn2;
    reg L10_1;
    wire p2_domand1;
    wire i1_domand1;
    wire p3_domand1;
    wire i2_domand1;
    reg x1_0_inp_reg;
    reg Q4_0_reg;
    wire p1_domand1;
    reg x1_1_inp_reg;
    reg Q4_1_reg;
    wire p4_domand1;
    reg i1_domand1_reg;
    wire T2_0;
    reg i2_domand1_reg;
    wire T2_1;
    wire Q2_0;
    wire L4_0;
    wire Q7_0;
    wire Q6_0;
    wire Q2_1;
    wire L4_1;
    wire Q7_1;
    wire Q6_1;
    wire p2_domand2;
    reg r_inp_reg;
    wire i1_domand2;
    wire p3_domand2;
    wire i2_domand2;
    reg Q2_0_reg;
    reg Q3_0_reg;
    wire p1_domand2;
    reg Q2_1_reg;
    reg Q3_1_reg;
    wire p4_domand2;
    reg i1_domand2_reg;
    wire T1_0;
    reg i2_domand2_reg;
    wire T1_1;
    wire p2_domand3;
    wire i1_domand3;
    wire p3_domand3;
    wire i2_domand3;
    reg Q6_0_reg;
    reg Q7_0_reg;
    wire p1_domand3;
    reg Q6_1_reg;
    reg Q7_1_reg;
    wire p4_domand3;
    reg i1_domand3_reg;
    wire T3_0;
    reg i2_domand3_reg;
    wire T3_1;
    reg T0_0_reg;
    wire L7_0;
    wire L11_0;
    reg T0_1_reg;
    wire L7_1;
    wire L11_1;
    reg T2_0_reg;
    wire Y0_01;
    wire Y1_01;
    reg T2_1_reg;
    wire Y0_11;
    wire Y1_11;
    reg z3_assgn3_reg;
    wire z7_assgn7;
    wire z9_assgn9;
    reg L5_0_reg;
    wire z11_assgn11;
    reg z5_assgn5_reg;
    wire z13_assgn13;
    wire z15_assgn15;
    reg L5_1_reg;
    wire z17_assgn17;

    assign x0_0_inp = x0_0;
    assign x1_0_inp = x1_0;
    assign x2_0_inp = x2_0;
    assign x3_0_inp = x3_0;
    assign x0_1_inp = x0_1;
    assign x1_1_inp = x1_1;
    assign x2_1_inp = x2_1;
    assign x3_1_inp = x3_1;
    assign r_inp = r;
    assign L0_0 = (x1_0_inp ^ x2_0_inp);
    assign L1_0 = (x0_0_inp ^ x1_0_inp);
    assign z239_assgn239 = x0_0_inp;
    assign z241_assgn241 = x2_0_inp;
    assign L8_0 = (z46_assgn46 ^ z45_assgn45);
    assign L5_0 = (x0_0_inp_reg ^ z3_assgn3);
    assign L0_1 = (x1_1_inp ^ x2_1_inp);
    assign L1_1 = (x0_1_inp ^ x1_1_inp);
    assign z251_assgn251 = x0_1_inp;
    assign z253_assgn253 = x2_1_inp;
    assign L8_1 = (z54_assgn54 ^ z53_assgn53);
    assign L5_1 = (x0_1_inp_reg ^ z5_assgn5);
    assign Q0_0 = !L0_0;
    assign Q1_0 = !L1_0;
    assign Q3_0 = !z3_assgn3;
    assign Q4_0 = !x2_0_inp;
    assign Q0_1 = !L0_1;
    assign Q1_1 = !L1_1;
    assign Q3_1 = !z5_assgn5;
    assign Q4_1 = !x2_1_inp;
    assign L2_0 = (Q1_0_reg ^ x2_0_inp_reg);
    assign L3_0 = (Q0_0_reg ^ z3_assgn3);
    assign L2_1 = (Q1_1_reg ^ x2_1_inp_reg);
    assign L3_1 = (Q0_1_reg ^ z5_assgn5);
    assign p2_domand0 = (Q0_0 & Q1_1);
    assign i1_domand0 = (p2_domand0 ^ r_inp);
    assign p3_domand0 = (Q0_1 & Q1_0);
    assign i2_domand0 = (p3_domand0 ^ r_inp);
    assign p1_domand0 = (Q0_0_reg & Q1_0_reg);
    assign p4_domand0 = (Q0_1_reg & Q1_1_reg);
    assign T0_0 = (i1_domand0_reg ^ p1_domand0);
    assign T0_1 = (i2_domand0_reg ^ p4_domand0);
    assign z1_assgn1 = !L2_0;
    assign z2_assgn2 = !L2_1;
    assign p2_domand1 = (x1_0_inp & Q4_1);
    assign i1_domand1 = (p2_domand1 ^ r_inp);
    assign p3_domand1 = (x1_1_inp & Q4_0);
    assign i2_domand1 = (p3_domand1 ^ r_inp);
    assign p1_domand1 = (x1_0_inp_reg & Q4_0_reg);
    assign p4_domand1 = (x1_1_inp_reg & Q4_1_reg);
    assign T2_0 = (i1_domand1_reg ^ p1_domand1);
    assign T2_1 = (i2_domand1_reg ^ p4_domand1);
    assign Q2_0 = (T0_0 ^ L2_0);
    assign L4_0 = (T0_0 ^ T2_0);
    assign Q7_0 = (T0_0 ^ L5_0);
    assign Q6_0 = (L4_0 ^ L3_0);
    assign Q2_1 = (T0_1 ^ L2_1);
    assign L4_1 = (T0_1 ^ T2_1);
    assign Q7_1 = (T0_1 ^ L5_1);
    assign Q6_1 = (L4_1 ^ L3_1);
    assign p2_domand2 = (Q2_0 & Q3_1);
    assign i1_domand2 = (p2_domand2 ^ r_inp_reg);
    assign p3_domand2 = (Q2_1 & Q3_0);
    assign i2_domand2 = (p3_domand2 ^ r_inp_reg);
    assign p1_domand2 = (Q2_0_reg & Q3_0_reg);
    assign p4_domand2 = (Q2_1_reg & Q3_1_reg);
    assign T1_0 = (i1_domand2_reg ^ p1_domand2);
    assign T1_1 = (i2_domand2_reg ^ p4_domand2);
    assign p2_domand3 = (Q6_0 & Q7_1);
    assign i1_domand3 = (p2_domand3 ^ r_inp_reg);
    assign p3_domand3 = (Q6_1 & Q7_0);
    assign i2_domand3 = (p3_domand3 ^ r_inp_reg);
    assign p1_domand3 = (Q6_0_reg & Q7_0_reg);
    assign p4_domand3 = (Q6_1_reg & Q7_1_reg);
    assign T3_0 = (i1_domand3_reg ^ p1_domand3);
    assign T3_1 = (i2_domand3_reg ^ p4_domand3);
    assign L7_0 = (T0_0_reg ^ T1_0);
    assign L11_0 = (T1_0 ^ L10_0);
    assign L7_1 = (T0_1_reg ^ T1_1);
    assign L11_1 = (T1_1 ^ L10_1);
    assign Y0_01 = (L7_0 ^ T2_0_reg);
    assign Y1_01 = (L8_0 ^ T3_0);
    assign Y0_11 = (L7_1 ^ T2_1_reg);
    assign Y1_11 = (L8_1 ^ T3_1);
    assign z7_assgn7 = (z3_assgn3_reg ^ Y0_01);
    assign z9_assgn9 = (L11_0 ^ T2_0_reg);
    assign z11_assgn11 = (T2_0_reg ^ L5_0_reg);
    assign z13_assgn13 = (z5_assgn5_reg ^ Y0_11);
    assign z15_assgn15 = (L11_1 ^ T2_1_reg);
    assign z17_assgn17 = (T2_1_reg ^ L5_1_reg);

    always @* begin
        z3_assgn3 <= x3_0_inp;
        z5_assgn5 <= x3_1_inp;
        z239_assgn2390 <= z239_assgn239;
        z45_assgn45 <= z239_assgn2390;
        z241_assgn2410 <= z241_assgn241;
        z46_assgn46 <= z241_assgn2410;
        x0_0_inp_reg <= x0_0_inp;
        z251_assgn2510 <= z251_assgn251;
        z53_assgn53 <= z251_assgn2510;
        z253_assgn2530 <= z253_assgn253;
        z54_assgn54 <= z253_assgn2530;
        x0_1_inp_reg <= x0_1_inp;
        Q1_0_reg <= Q1_0;
        x2_0_inp_reg <= x2_0_inp;
        Q0_0_reg <= Q0_0;
        Q1_1_reg <= Q1_1;
        x2_1_inp_reg <= x2_1_inp;
        Q0_1_reg <= Q0_1;
        i1_domand0_reg <= i1_domand0;
        i2_domand0_reg <= i2_domand0;
        L10_0 <= z1_assgn1;
        L10_1 <= z2_assgn2;
        x1_0_inp_reg <= x1_0_inp;
        Q4_0_reg <= Q4_0;
        x1_1_inp_reg <= x1_1_inp;
        Q4_1_reg <= Q4_1;
        i1_domand1_reg <= i1_domand1;
        i2_domand1_reg <= i2_domand1;
        r_inp_reg <= r_inp;
        Q2_0_reg <= Q2_0;
        Q3_0_reg <= Q3_0;
        Q2_1_reg <= Q2_1;
        Q3_1_reg <= Q3_1;
        i1_domand2_reg <= i1_domand2;
        i2_domand2_reg <= i2_domand2;
        Q6_0_reg <= Q6_0;
        Q7_0_reg <= Q7_0;
        Q6_1_reg <= Q6_1;
        Q7_1_reg <= Q7_1;
        i1_domand3_reg <= i1_domand3;
        i2_domand3_reg <= i2_domand3;
        T0_0_reg <= T0_0;
        T0_1_reg <= T0_1;
        T2_0_reg <= T2_0;
        T2_1_reg <= T2_1;
        z3_assgn3_reg <= z3_assgn3;
        Y0_0 <= z7_assgn7;
        Y1_0 <= (L7_0 ^ Y1_01);
        Y2_0 <= z9_assgn9;
        L5_0_reg <= L5_0;
        Y3_0 <= z11_assgn11;
        z5_assgn5_reg <= z5_assgn5;
        Y0_1 <= z13_assgn13;
        Y1_1 <= (L7_1 ^ Y1_11);
        Y2_1 <= z15_assgn15;
        L5_1_reg <= L5_1;
        Y3_1 <= z17_assgn17;
    end

endmodule

src/FunctionalCorrectness/PRESENT/present_tb.v
`timescale 1ns/1ns
module present_tb;

	
	parameter total_record = 498;//total number of plaintexts for which to check
    
    	reg clk, x0_0, x1_0, x2_0, x3_0, x0_1, x1_1, x2_1, x3_1, r;
	
	wire Y0_0, Y1_0, Y2_0, Y3_0, Y0_1, Y1_1, Y2_1, Y3_1;

	integer i, count;

	reg [3:0] out0Comb[0:total_record-1];
	reg [3:0] out1Comb[0:total_record-1];
	initial $readmemb("./InputPlaintext/out0Comb.txt",out0Comb);
	initial $readmemb("./InputPlaintext/out1Comb.txt",out1Comb);
//	initial clk = 1'b0;
 //   	initial ap_rst = 1'b1;
 //   	initial ap_start = 1'b1;
	sbox dut(
	.clk(clk),
	.x0_0(x0_0),
	.x1_0(x1_0),
	.x2_0(x2_0),
	.x3_0(x3_0),
	.x0_1(x0_1),
	.x1_1(x1_1),
	.x2_1(x2_1),
	.x3_1(x3_1),
        .r(r),
	.Y0_0(Y0_0),
	.Y1_0(Y1_0),
	.Y2_0(Y2_0),
	.Y3_0(Y3_0),
	
	.Y0_1(Y0_1),
	
	.Y1_1(Y1_1),
	
	.Y2_1(Y2_1),
	
	.Y3_1(Y3_1));
	
	always begin
	#5 clk = ~clk;
	end
	initial begin
		$dumpfile("sbox_vcd.vcd");
		$dumpvars();
		clk = 0;
		
		i = 0;
		count = 0;
		x0_0 = 0;
		x1_0 = 0;
		x2_0 = 0;
		x3_0 = 0;
		
		x0_1 = 0;
		x1_1 = 0;
		x2_1 = 0;
		x3_1 = 0;
		r = 0;
		
		
	end
	always @(negedge clk) begin
		if (i > total_record) begin
			$finish;
		end
		// else begin
		// 	if (count == 0) begin
			for (i = 0; i < total_record; i = i + 1) begin
				x0_0 = out0Comb[i][0];
				x1_0 = out0Comb[i][1];
				x2_0 = out0Comb[i][2];
				x3_0 = out0Comb[i][3];

				x0_1 = out1Comb[i][0];
				x1_1 = out1Comb[i][1];
				x2_1 = out1Comb[i][2];
				x3_1 = out1Comb[i][3];

				r = 0;
				#34
			
			 
				//$display("Test Case: %0d: %b%b%b%b  %b%b%b%b", i+1, x3_0, x2_0, x1_0, x0_0, x3_1, x2_1, x1_1, x0_1);
				//$display("Time     = %0t: %b%b%b%b  %b%b%b%b", $time,Y3_0, Y2_0, Y1_0, Y0_0, Y3_1, Y2_1, Y1_1, Y0_1);
				//$display("---------------------------------------------------------------");
				$display("%d  %b%b%b%b %b%b%b%b", i+1, x3_0 ^ x3_1, x2_0 ^ x2_1, x1_0 ^ x1_1, x0_0 ^ x0_1, Y0_0 ^ Y0_1, Y1_0 ^ Y1_1, Y2_0 ^ Y2_1, Y3_0 ^ Y3_1);

			end
			// end
			//$display("Test Case %0d: x3_0=%b, x2_0=%b, x1_0=%b, x0_0=%b, x3_1=%b, x2_1=%b, x1_1=%b, x0_1=%b,", i+1, x3_0, x2_0, x1_0, x0_0, x3_1, x2_1, x1_1, x0_1);
			//$display("Time=%0t: Outputs: Y0_0=%b, Y1_0=%b, Y2_0=%b, Y3_0=%b, Y0_1=%b, Y1_1=%b, Y2_1=%b, Y3_1=%b", $time, Y0_0, Y1_0, Y2_0, Y3_0, Y0_1, Y1_1, Y2_1, Y3_1);
			// count = (count + 1)%3;
		// end
		$finish;
	end
endmodule

src/FunctionalCorrectness/PRESENT/sbox_vcd.vcd
$date
	Wed Oct  2 00:28:34 2024
$end
$version
	Icarus Verilog
$end
$timescale
	1ns
$end
$scope module present_tb $end
$var wire 1 ! Y3_1 $end
$var wire 1 " Y3_0 $end
$var wire 1 # Y2_1 $end
$var wire 1 $ Y2_0 $end
$var wire 1 % Y1_1 $end
$var wire 1 & Y1_0 $end
$var wire 1 ' Y0_1 $end
$var wire 1 ( Y0_0 $end
$var parameter 32 ) total_record $end
$var reg 1 * clk $end
$var reg 1 + r $end
$var reg 1 , x0_0 $end
$var reg 1 - x0_1 $end
$var reg 1 . x1_0 $end
$var reg 1 / x1_1 $end
$var reg 1 0 x2_0 $end
$var reg 1 1 x2_1 $end
$var reg 1 2 x3_0 $end
$var reg 1 3 x3_1 $end
$var integer 32 4 count [31:0] $end
$var integer 32 5 i [31:0] $end
$scope module dut $end
$var wire 1 6 L0_0 $end
$var wire 1 7 L0_1 $end
$var wire 1 8 L11_0 $end
$var wire 1 9 L11_1 $end
$var wire 1 : L1_0 $end
$var wire 1 ; L1_1 $end
$var wire 1 < L2_0 $end
$var wire 1 = L2_1 $end
$var wire 1 > L3_0 $end
$var wire 1 ? L3_1 $end
$var wire 1 @ L4_0 $end
$var wire 1 A L4_1 $end
$var wire 1 B L5_0 $end
$var wire 1 C L5_1 $end
$var wire 1 D L7_0 $end
$var wire 1 E L7_1 $end
$var wire 1 F L8_0 $end
$var wire 1 G L8_1 $end
$var wire 1 H Q2_0 $end
$var wire 1 I Q2_1 $end
$var wire 1 J Q6_0 $end
$var wire 1 K Q6_1 $end
$var wire 1 L Q7_0 $end
$var wire 1 M Q7_1 $end
$var wire 1 N T0_0 $end
$var wire 1 O T0_1 $end
$var wire 1 P T1_0 $end
$var wire 1 Q T1_1 $end
$var wire 1 R T2_0 $end
$var wire 1 S T2_1 $end
$var wire 1 T T3_0 $end
$var wire 1 U T3_1 $end
$var wire 1 V Y0_01 $end
$var wire 1 W Y0_11 $end
$var wire 1 X Y1_01 $end
$var wire 1 Y Y1_11 $end
$var wire 1 * clk $end
$var wire 1 Z i1_domand0 $end
$var wire 1 [ i1_domand1 $end
$var wire 1 \ i1_domand2 $end
$var wire 1 ] i1_domand3 $end
$var wire 1 ^ i2_domand0 $end
$var wire 1 _ i2_domand1 $end
$var wire 1 ` i2_domand2 $end
$var wire 1 a i2_domand3 $end
$var wire 1 b p1_domand0 $end
$var wire 1 c p1_domand1 $end
$var wire 1 d p1_domand2 $end
$var wire 1 e p1_domand3 $end
$var wire 1 f p2_domand0 $end
$var wire 1 g p2_domand1 $end
$var wire 1 h p2_domand2 $end
$var wire 1 i p2_domand3 $end
$var wire 1 j p3_domand0 $end
$var wire 1 k p3_domand1 $end
$var wire 1 l p3_domand2 $end
$var wire 1 m p3_domand3 $end
$var wire 1 n p4_domand0 $end
$var wire 1 o p4_domand1 $end
$var wire 1 p p4_domand2 $end
$var wire 1 q p4_domand3 $end
$var wire 1 + r $end
$var wire 1 r r_inp $end
$var wire 1 , x0_0 $end
$var wire 1 s x0_0_inp $end
$var wire 1 - x0_1 $end
$var wire 1 t x0_1_inp $end
$var wire 1 . x1_0 $end
$var wire 1 u x1_0_inp $end
$var wire 1 / x1_1 $end
$var wire 1 v x1_1_inp $end
$var wire 1 0 x2_0 $end
$var wire 1 w x2_0_inp $end
$var wire 1 1 x2_1 $end
$var wire 1 x x2_1_inp $end
$var wire 1 2 x3_0 $end
$var wire 1 y x3_0_inp $end
$var wire 1 3 x3_1 $end
$var wire 1 z x3_1_inp $end
$var wire 1 { z11_assgn11 $end
$var wire 1 | z13_assgn13 $end
$var wire 1 } z15_assgn15 $end
$var wire 1 ~ z17_assgn17 $end
$var wire 1 !" z239_assgn239 $end
$var wire 1 "" z241_assgn241 $end
$var wire 1 #" z251_assgn251 $end
$var wire 1 $" z253_assgn253 $end
$var wire 1 %" z7_assgn7 $end
$var wire 1 &" z9_assgn9 $end
$var wire 1 '" z2_assgn2 $end
$var wire 1 (" z1_assgn1 $end
$var wire 1 )" Q4_1 $end
$var wire 1 *" Q4_0 $end
$var wire 1 +" Q3_1 $end
$var wire 1 ," Q3_0 $end
$var wire 1 -" Q1_1 $end
$var wire 1 ." Q1_0 $end
$var wire 1 /" Q0_1 $end
$var wire 1 0" Q0_0 $end
$var reg 1 1" L10_0 $end
$var reg 1 2" L10_1 $end
$var reg 1 3" L5_0_reg $end
$var reg 1 4" L5_1_reg $end
$var reg 1 5" Q0_0_reg $end
$var reg 1 6" Q0_1_reg $end
$var reg 1 7" Q1_0_reg $end
$var reg 1 8" Q1_1_reg $end
$var reg 1 9" Q2_0_reg $end
$var reg 1 :" Q2_1_reg $end
$var reg 1 ;" Q3_0_reg $end
$var reg 1 <" Q3_1_reg $end
$var reg 1 =" Q4_0_reg $end
$var reg 1 >" Q4_1_reg $end
$var reg 1 ?" Q6_0_reg $end
$var reg 1 @" Q6_1_reg $end
$var reg 1 A" Q7_0_reg $end
$var reg 1 B" Q7_1_reg $end
$var reg 1 C" T0_0_reg $end
$var reg 1 D" T0_1_reg $end
$var reg 1 E" T2_0_reg $end
$var reg 1 F" T2_1_reg $end
$var reg 1 ( Y0_0 $end
$var reg 1 ' Y0_1 $end
$var reg 1 & Y1_0 $end
$var reg 1 % Y1_1 $end
$var reg 1 $ Y2_0 $end
$var reg 1 # Y2_1 $end
$var reg 1 " Y3_0 $end
$var reg 1 ! Y3_1 $end
$var reg 1 G" i1_domand0_reg $end
$var reg 1 H" i1_domand1_reg $end
$var reg 1 I" i1_domand2_reg $end
$var reg 1 J" i1_domand3_reg $end
$var reg 1 K" i2_domand0_reg $end
$var reg 1 L" i2_domand1_reg $end
$var reg 1 M" i2_domand2_reg $end
$var reg 1 N" i2_domand3_reg $end
$var reg 1 O" r_inp_reg $end
$var reg 1 P" x0_0_inp_reg $end
$var reg 1 Q" x0_1_inp_reg $end
$var reg 1 R" x1_0_inp_reg $end
$var reg 1 S" x1_1_inp_reg $end
$var reg 1 T" x2_0_inp_reg $end
$var reg 1 U" x2_1_inp_reg $end
$var reg 1 V" z239_assgn2390 $end
$var reg 1 W" z241_assgn2410 $end
$var reg 1 X" z251_assgn2510 $end
$var reg 1 Y" z253_assgn2530 $end
$var reg 1 Z" z3_assgn3 $end
$var reg 1 [" z3_assgn3_reg $end
$var reg 1 \" z45_assgn45 $end
$var reg 1 ]" z46_assgn46 $end
$var reg 1 ^" z53_assgn53 $end
$var reg 1 _" z54_assgn54 $end
$var reg 1 `" z5_assgn5 $end
$var reg 1 a" z5_assgn5_reg $end
$upscope $end
$upscope $end
$enddefinitions $end
$comment Show the parameter values. $end
$dumpall
b111110010 )
$end
#0
$dumpvars
0a"
0`"
0_"
0^"
0]"
0\"
0["
0Z"
0Y"
0X"
0W"
0V"
0U"
0T"
0S"
0R"
0Q"
0P"
0O"
0N"
1M"
0L"
1K"
0J"
1I"
0H"
1G"
0F"
0E"
0D"
0C"
0B"
0A"
1@"
1?"
1>"
1="
1<"
1;"
1:"
19"
18"
17"
16"
15"
04"
03"
02"
01"
10"
1/"
1."
1-"
1,"
1+"
1*"
1)"
0("
0'"
0&"
0%"
0$"
0#"
0""
0!"
0~
0}
0|
0{
0z
0y
0x
0w
0v
0u
0t
0s
0r
0q
1p
0o
1n
0m
1l
0k
1j
0i
1h
0g
1f
0e
1d
0c
1b
0a
1`
0_
1^
0]
1\
0[
1Z
0Y
0X
0W
0V
0U
0T
0S
0R
0Q
0P
0O
0N
0M
0L
1K
1J
1I
1H
0G
0F
0E
0D
0C
0B
0A
0@
1?
1>
1=
1<
0;
0:
09
08
07
06
b0 5
b0 4
03
02
01
00
0/
0.
0-
0,
0+
0*
0(
0'
0&
0%
0$
0#
0"
0!
$end
#5
1*
#10
1'
1$
1&
1|
1W
1&"
1Y
1X
0p
1E
0d
18
1G
1F
0M"
0@"
1B"
0I"
0:"
1D"
0?"
09"
11"
1_"
1]"
0`
0l
0K
0\
0I
1A
1M
0h
1O
0J
0H
0n
0b
0>
1("
0<
0G"
08"
05"
0>"
1S"
0="
1U"
1T"
1Y"
1W"
0Z
0f
0-"
1;
00"
16
1$"
0)"
1x
11
1v
1/
1""
0*"
1w
10
0*
#15
1*
#20
0*
#25
1*
#30
0*
#35
1*
#40
0*
#44
0'
0&
1!
0$
0|
0X
0W
0&"
0Y
1T
1p
1d
1~
0E
08
0G
1M"
1J"
1I"
0@"
1?"
1:"
19"
14"
0D"
01"
1^"
1`
1]
1\
1l
1i
1h
1I
0A
0K
1J
1H
0O
0?
1>
0("
1<
1C
0K"
06"
15"
07"
0S"
1R"
1Q"
1X"
0^
0j
0/"
17
10"
06
0."
1:
0v
0/
1#"
1t
1-
1u
1.
b1 5
#45
1*
#50
0*
#55
1*
#60
0*
#65
1*
#70
0*
#75
1*
#78
1(
0!
1#
1%
1"
1$
0&
1%"
1X
1V
1}
1&"
1Y
0T
0p
0~
1{
1D
19
18
1G
0J"
0?"
0M"
0B"
0:"
04"
13"
1C"
12"
11"
0^"
0]"
1\"
0`
0]
0J
0l
0i
1@
0I
0M
1N
1'"
0=
1("
0<
0C
1B
1G"
18"
1="
0R"
0T"
0Q"
0X"
1P"
0W"
1V"
1Z
1f
1-"
0;
0#"
0t
0-
0""
1*"
0w
00
0u
0.
1!"
1s
1,
b10 5
#80
0*
#85
1*
#90
0*
#95
1*
#100
0*
#105
1*
#110
0*
#112
1$
0#
1&
0(
1!
0%
0'
0X
1&"
1W
1T
0%"
1D
0}
1U
1E
1e
0d
0V
0P
09
08
1~
0|
0G
1N"
1@"
1?"
0M"
1D"
1A"
0:"
09"
03"
1E"
0B"
0I"
02"
01"
14"
1a"
0<"
0_"
1]"
0\"
1a
1m
1K
0`
1J
1A
0l
0@
1O
0I
0H
1L
0\
0M
1R
1n
0'"
1=
0("
1<
0B
0h
1C
1H"
16"
1>"
0="
1R"
0U"
1T"
0Y"
0P"
1W"
0V"
0+"
1`"
1[
1/"
07
1g
1z
13
0$"
1)"
0x
01
1""
0*"
1w
10
1u
1.
0!"
0s
0,
b11 5
#115
1*
#120
0*
#125
1*
#130
0*
#135
1*
#140
0*
#145
1*
#146
1#
0!
0%
1'
1$
0(
1}
19
18
1W
0T
1Q
0X
1P
1D
0~
1&"
1V
1E
0e
1|
0%"
1p
0F
1I"
1N"
19"
0C"
1@"
1:"
04"
0E"
0D"
1A"
0?"
0a"
13"
1["
1<"
0;"
0]"
1\
1h
1a
1H
1m
1I
0A
0N
1K
0J
1L
0O
0R
1b
1?
0C
0>
1B
1K"
0H"
17"
1="
0R"
0T"
0W"
1+"
0`"
0,"
1Z"
1^
1j
0[
1."
0:
0g
0z
03
1y
12
0""
1*"
0w
00
0u
0.
b100 5
#150
0*
#155
1*
#160
0*
#165
1*
#170
0*
#175
1*
#180
0$
1%
0(
1!
0&
0&"
0%"
1X
08
0Y
1V
1T
0P
0U
1~
1D
1J"
0I"
0N"
1?"
1B"
0@"
0A"
09"
14"
1C"
1_"
1^"
1]
0\
1i
0a
0h
1J
0m
0H
1@
0L
0K
1M
1N
0?
0n
1C
0K"
0G"
06"
08"
0>"
1U"
1Q"
1Y"
1X"
0^
0Z
0j
0f
0/"
17
0-"
1;
0*
1$"
0)"
1x
11
1#"
1t
1-
b101 5
#185
1*
#190
0*
#195
1*
#200
0*
#205
1*
#210
0*
#214
1'
0!
1#
1%
0&
0(
0X
1|
0V
0E
09
1Y
0T
1q
0~
1}
1W
0D
0Q
0%"
1d
1G
0J"
1I"
1N"
0?"
1@"
1A"
19"
1F"
0C"
1M"
0["
1;"
0_"
1]"
1\"
0]
1\
0i
1a
1h
0J
1m
1K
1H
0@
1L
1A
0N
1S
1`
0b
1o
1l
18"
05"
07"
1>"
1S"
0="
0U"
1T"
0Y"
1P"
1W"
1V"
1,"
0Z"
1-"
0;
00"
16
0."
1:
0$"
1)"
0x
01
1v
1/
0y
02
1""
0*"
1w
10
1!"
1s
1,
b110 5
#215
1*
#220
0*
#225
1*
#230
0*
#235
1*
#240
0*
#245
1*
#248
1(
1$
1!
1#
1%
0'
0&
1%"
1V
1&"
1E
19
1D
18
1Q
0Y
1X
0q
1~
1}
1W
1P
0|
0p
0G
1F
0N"
0@"
0F"
0I"
1a"
0<"
0^"
0]"
0a
0m
0K
0A
0S
0\
1n
0o
1c
0h
1K"
1H"
16"
17"
0S"
1="
1R"
0T"
0Q"
0X"
0W"
0+"
1`"
1^
1j
1[
1/"
07
1."
0:
1g
1z
13
0v
0/
0#"
0t
0-
0""
1*"
0w
00
1u
1.
b111 5
#250
0*
#255
1*
#260
0*
#265
1*
#270
0*
#275
1*
#280
0*
#282
0#
0%
1&
1(
0'
0"
1$
0W
0}
0E
09
1%"
0D
08
0Q
1e
0{
1&"
1V
0P
0|
1p
1J"
1?"
1E"
1I"
0a"
1<"
1_"
1^"
1]
1i
1J
1@
1\
1R
0n
1h
0K"
0H"
06"
08"
0>"
1U"
1Q"
1Y"
1X"
1+"
0`"
0^
0j
0[
0/"
17
0g
0-"
1;
0z
03
1$"
0)"
1x
11
1#"
1t
1-
b1000 5
#285
1*
#290
0*
#295
1*
#300
0*
#305
1*
#310
0*
#315
1*
#316
1"
0(
0%"
0d
1{
0V
18
1J"
0I"
1?"
09"
0E"
11"
1]
0\
1i
0h
0@
1J
0H
0R
1>
1("
0<
0c
15"
07"
0R"
10"
06
0."
1:
0u
0.
b1001 5
#320
0*
#325
1*
#330
0*
#335
1*
#340
0*
#345
1*
#350
1'
0!
1#
1%
0&
1|
1Y
1q
0~
1}
1W
1D
08
1G
1N"
1@"
1F"
03"
1E"
1C"
01"
0_"
1]"
0\"
1a
1m
1K
1A
1S
1N
1R
1o
0("
1<
0B
1G"
1H"
18"
1>"
1S"
0="
1R"
0U"
1T"
0Y"
0P"
1W"
0V"
1Z
1f
1[
1-"
0;
1g
0*
0$"
1)"
0x
01
1v
1/
1""
0*"
1w
10
1u
1.
0!"
0s
0,
b1010 5
#355
1*
#360
0*
#365
1*
#370
0*
#375
1*
#380
0*
#384
1!
0#
0'
1(
0|
1%"
0q
0e
1d
1~
0}
0W
1V
18
0J"
0N"
0@"
0?"
1I"
0A"
19"
13"
0F"
0E"
11"
0]"
1\"
0]
0i
1\
0a
0K
0J
1h
0m
0A
1@
1H
0L
0S
0R
1("
0<
1B
1L"
0H"
1="
0R"
0T"
1P"
0W"
1V"
1_
0[
1k
0g
0""
1*"
0w
00
0u
0.
1!"
1s
1,
b1011 5
#385
1*
#390
0*
#395
1*
#400
0*
#405
1*
#410
0*
#415
1*
#418
1'
1#
0%
1$
1&
0!
0(
1|
1W
1}
1V
1E
19
1&"
0X
1U
1P
1D
0~
1Q
18
0%"
0d
0G
0F
1N"
1A"
1I"
0C"
0B"
1@"
19"
04"
0?"
0M"
01"
1["
0;"
0^"
0\"
1a
1\
1m
0@
1L
1h
1K
0N
1H
0M
0`
0J
1n
1?
1b
0("
1<
0o
0C
0l
0>
0L"
1K"
16"
17"
0S"
0Q"
0X"
0P"
0V"
0,"
1Z"
1^
0_
1j
1/"
07
0k
1."
0:
0v
0/
0#"
0t
0-
1y
12
0!"
0s
0,
b1100 5
#420
0*
#425
1*
#430
0*
#435
1*
#440
0*
#445
1*
#450
0*
